makedalytics.py
makedalytics-0.0.9.dist-info/LICENSE
makedalytics-0.0.9.dist-info/METADATA
makedalytics-0.0.9.dist-info/WHEEL
makedalytics-0.0.9.dist-info/top_level.txt
makedalytics-0.0.9.dist-info/RECORD
