Metadata-Version: 2.1
Name: makedalytics
Version: 0.0.9
Summary: Python library for reproducible data analytics of dataframes, text and images
Home-page: https://github.com/drcandacemakedamoore/makedalytics
Author: doctormakeda@gmail.com
Author-email: doctormakeda@gmail.com
Maintainer: doctormakeda@gmail.com
Maintainer-email: doctormakeda@gmail.com
License: MIT
Platform: UNKNOWN
Requires-Dist: pip
